{
    "forecastseries_configs": [
        {
            "name": "Forge April 24 Stage 9",
            "description": "Forecasts Stage 9 of the April 2024 FORGE experiment",
            "starttime": "2024-04-06T06:00:00",
            "endtime": "2024-04-06T17:00:00",
            "forecastinterval": 900,
            "tags": [
                "INDUCED",
                "FORGE"
            ],
            "injectionplan_dir": "plans_9",
            "injectionplan_filenames": [
                "double.json",
                "half.json",
                "planned.json",
                "shut-in.json"
            ],
            "altitudemin": -150.0,
            "altitudemax": 150.0,
            "boundingbox": {
                "x_min": 334491.1891,
                "x_max": 334791.18910,
                "y_min": 4263293.6931,
                "y_max": 4263593.6931,
                "srid": "epsg:26912"
            }
        }
    ]
}
