{"publicid":"a7233908-572a-44a4-9c86-0bb624415b9b","longitude":{"value":-112.89638854692598},"latitude":{"value":38.50402239072762},"altitude":{"value":0.038027779},"bedrockaltitude":{},"measureddepth":{"value":3000.0},"sections":[{"publicid":"61ba3dbb-68b7-47c0-aa91-578d16c651f2","starttime":"2022-01-01T06:00:16","endtime":"2022-04-21T16:29:23","toplongitude":{"value":-112.89638966954868},"toplatitude":{"value":38.504021471443096},"topaltitude":{"value":0.0},"bottomlongitude":{"value":-112.89638966954868},"bottomlatitude":{"value":38.504021471443096},"bottomaltitude":{"value":3000.0},"topmeasureddepth":{"value":0.0},"bottommeasureddepth":{"value":3000.0},"holediameter":{},"casingdiameter":{},"topclosed":true,"bottomclosed":true,"hydraulics":[{"datetime":{"value":"2022-04-21T16:29:23"},"bottomtemperature":{},"bottomflow":{},"bottompressure":{},"toptemperature":{},"topflow":{"value":0.0},"toppressure":{"value":21913357.38968048},"fluiddensity":{},"fluidviscosity":{},"fluidph":{}},{"datetime":{"value":"2022-04-21T13:00:23"},"bottomtemperature":{},"bottomflow":{},"bottompressure":{},"toptemperature":{},"topflow":{"value":0.0},"toppressure":{"value":102287.2866884165},"fluiddensity":{},"fluidviscosity":{},"fluidph":{}},{"datetime":{"value":"2022-04-21T13:01:23"},"bottomtemperature":{},"bottomflow":{},"bottompressure":{},"toptemperature":{},"topflow":{"value":0.0},"toppressure":{"value":103390.44785481649},"fluiddensity":{},"fluidviscosity":{},"fluidph":{}},{"datetime":{"value":"2022-04-21T13:02:23"},"bottomtemperature":{},"bottomflow":{},"bottompressure":{},"toptemperature":{},"topflow":{"value":0.0},"toppressure":{"value":102129.281833854},"fluiddensity":{},"fluidviscosity":{},"fluidph":{}},{"datetime":{"value":"2022-04-21T13:03:23"},"bottomtemperature":{},"bottomflow":{},"bottompressure":{},"toptemperature":{},"topflow":{"value":0.0},"toppressure":{"value":105335.80362419},"fluiddensity":{},"fluidviscosity":{},"fluidph":{}},{"datetime":{"value":"2022-04-21T13:04:23"},"bottomtemperature":{},"bottomflow":{},"bottompressure":{},"toptemperature":{},"topflow":{"value":0.0},"toppressure":{"value":103182.80074776598},"fluiddensity":{},"fluidviscosity":{},"fluidph":{}},{"datetime":{"value":"2022-04-21T13:05:23"},"bottomtemperature":{},"bottomflow":{},"bottompressure":{},"toptemperature":{},"topflow":{"value":0.0},"toppressure":{"value":102765.5530190995},"fluiddensity":{},"fluidviscosity":{},"fluidph":{}},{"datetime":{"value":"2022-04-21T13:06:23"},"bottomtemperature":{},"bottomflow":{},"bottompressure":{},"toptemperature":{},"topflow":{"value":0.0},"toppressure":{"value":103390.67768005951},"fluiddensity":{},"fluidviscosity":{},"fluidph":{}},{"datetime":{"value":"2022-04-21T13:07:23"},"bottomtemperature":{},"bottomflow":{},"bottompressure":{},"toptemperature":{},"topflow":{"value":0.0},"toppressure":{"value":101342.13037657898},"fluiddensity":{},"fluidviscosity":{},"fluidph":{}},{"datetime":{"value":"2022-04-21T13:08:23"},"bottomtemperature":{},"bottomflow":{},"bottompressure":{},"toptemperature":{},"topflow":{"value":0.0},"toppressure":{"value":99606.6050540645},"fluiddensity":{},"fluidviscosity":{},"fluidph":{}},{"datetime":{"value":"2022-04-21T13:09:23"},"bottomtemperature":{},"bottomflow":{},"bottompressure":{},"toptemperature":{},"topflow":{"value":0.0},"toppressure":{"value":101425.6718524095},"fluiddensity":{},"fluidviscosity":{},"fluidph":{}},{"datetime":{"value":"2022-04-21T13:10:23"},"bottomtemperature":{},"bottomflow":{},"bottompressure":{},"toptemperature":{},"topflow":{"value":0.0},"toppressure":{"value":103480.884087937},"fluiddensity":{},"fluidviscosity":{},"fluidph":{}},{"datetime":{"value":"2022-04-21T13:11:23"},"bottomtemperature":{},"bottomflow":{},"bottompressure":{},"toptemperature":{},"topflow":{"value":0.0},"toppressure":{"value":105605.84828471499},"fluiddensity":{},"fluidviscosity":{},"fluidph":{}},{"datetime":{"value":"2022-04-21T13:12:23"},"bottomtemperature":{},"bottomflow":{},"bottompressure":{},"toptemperature":{},"topflow":{"value":0.0},"toppressure":{"value":102898.277096932},"fluiddensity":{},"fluidviscosity":{},"fluidph":{}},{"datetime":{"value":"2022-04-21T13:13:23"},"bottomtemperature":{},"bottomflow":{},"bottompressure":{},"toptemperature":{},"topflow":{"value":0.0},"toppressure":{"value":102383.238727369},"fluiddensity":{},"fluidviscosity":{},"fluidph":{}},{"datetime":{"value":"2022-04-21T13:14:23"},"bottomtemperature":{},"bottomflow":{},"bottompressure":{},"toptemperature":{},"topflow":{"value":0.0},"toppressure":{"value":100670.69592915449},"fluiddensity":{},"fluidviscosity":{},"fluidph":{}},{"datetime":{"value":"2022-04-21T13:15:23"},"bottomtemperature":{},"bottomflow":{},"bottompressure":{},"toptemperature":{},"topflow":{"value":0.0},"toppressure":{"value":102367.2658729805},"fluiddensity":{},"fluidviscosity":{},"fluidph":{}},{"datetime":{"value":"2022-04-21T13:16:23"},"bottomtemperature":{},"bottomflow":{},"bottompressure":{},"toptemperature":{},"topflow":{"value":0.0},"toppressure":{"value":101654.80761968049},"fluiddensity":{},"fluidviscosity":{},"fluidph":{}},{"datetime":{"value":"2022-04-21T13:17:23"},"bottomtemperature":{},"bottomflow":{},"bottompressure":{},"toptemperature":{},"topflow":{"value":0.0},"toppressure":{"value":101169.53161908599},"fluiddensity":{},"fluidviscosity":{},"fluidph":{}},{"datetime":{"value":"2022-04-21T13:18:23"},"bottomtemperature":{},"bottomflow":{},"bottompressure":{},"toptemperature":{},"topflow":{"value":0.0},"toppressure":{"value":99914.91561754899},"fluiddensity":{},"fluidviscosity":{},"fluidph":{}},{"datetime":{"value":"2022-04-21T13:19:23"},"bottomtemperature":{},"bottomflow":{},"bottompressure":{},"toptemperature":{},"topflow":{"value":0.0},"toppressure":{"value":100507.29018138148},"fluiddensity":{},"fluidviscosity":{},"fluidph":{}},{"datetime":{"value":"2022-04-21T13:20:23"},"bottomtemperature":{},"bottomflow":{},"bottompressure":{},"toptemperature":{},"topflow":{"value":0.0},"toppressure":{"value":102091.820319245},"fluiddensity":{},"fluidviscosity":{},"fluidph":{}},{"datetime":{"value":"2022-04-21T13:21:23"},"bottomtemperature":{},"bottomflow":{},"bottompressure":{},"toptemperature":{},"topflow":{"value":0.0},"toppressure":{"value":101601.02851281849},"fluiddensity":{},"fluidviscosity":{},"fluidph":{}},{"datetime":{"value":"2022-04-21T13:22:23"},"bottomtemperature":{},"bottomflow":{},"bottompressure":{},"toptemperature":{},"topflow":{"value":0.0},"toppressure":{"value":99357.35957803098},"fluiddensity":{},"fluidviscosity":{},"fluidph":{}},{"datetime":{"value":"2022-04-21T13:23:23"},"bottomtemperature":{},"bottomflow":{},"bottompressure":{},"toptemperature":{},"topflow":{"value":0.0},"toppressure":{"value":102147.55294067248},"fluiddensity":{},"fluidviscosity":{},"fluidph":{}},{"datetime":{"value":"2022-04-21T13:24:23"},"bottomtemperature":{},"bottomflow":{},"bottompressure":{},"toptemperature":{},"topflow":{"value":0.0},"toppressure":{"value":100351.6984918705},"fluiddensity":{},"fluidviscosity":{},"fluidph":{}},{"datetime":{"value":"2022-04-21T13:25:23"},"bottomtemperature":{},"bottomflow":{},"bottompressure":{},"toptemperature":{},"topflow":{"value":0.0},"toppressure":{"value":100822.26567691298},"fluiddensity":{},"fluidviscosity":{},"fluidph":{}},{"datetime":{"value":"2022-04-21T13:26:23"},"bottomtemperature":{},"bottomflow":{},"bottompressure":{},"toptemperature":{},"topflow":{"value":0.0},"toppressure":{"value":100405.362686111},"fluiddensity":{},"fluidviscosity":{},"fluidph":{}},{"datetime":{"value":"2022-04-21T13:27:23"},"bottomtemperature":{},"bottomflow":{},"bottompressure":{},"toptemperature":{},"topflow":{"value":0.0},"toppressure":{"value":98566.071266382},"fluiddensity":{},"fluidviscosity":{},"fluidph":{}},{"datetime":{"value":"2022-04-21T13:28:23"},"bottomtemperature":{},"bottomflow":{},"bottompressure":{},"toptemperature":{},"topflow":{"value":0.0},"toppressure":{"value":96205.30637028598},"fluiddensity":{},"fluidviscosity":{},"fluidph":{}},{"datetime":{"value":"2022-04-21T13:29:23"},"bottomtemperature":{},"bottomflow":{},"bottompressure":{},"toptemperature":{},"topflow":{"value":0.0},"toppressure":{"value":96122.33945756298},"fluiddensity":{},"fluidviscosity":{},"fluidph":{}},{"datetime":{"value":"2022-04-21T13:30:23"},"bottomtemperature":{},"bottomflow":{},"bottompressure":{},"toptemperature":{},"topflow":{"value":0.0},"toppressure":{"value":98044.94252787948},"fluiddensity":{},"fluidviscosity":{},"fluidph":{}},{"datetime":{"value":"2022-04-21T13:31:23"},"bottomtemperature":{},"bottomflow":{},"bottompressure":{},"toptemperature":{},"topflow":{"value":0.0},"toppressure":{"value":96968.78582753199},"fluiddensity":{},"fluidviscosity":{},"fluidph":{}},{"datetime":{"value":"2022-04-21T13:32:23"},"bottomtemperature":{},"bottomflow":{},"bottompressure":{},"toptemperature":{},"topflow":{"value":0.0},"toppressure":{"value":95997.084700128},"fluiddensity":{},"fluidviscosity":{},"fluidph":{}},{"datetime":{"value":"2022-04-21T13:33:23"},"bottomtemperature":{},"bottomflow":{},"bottompressure":{},"toptemperature":{},"topflow":{"value":0.0025677320987120993},"toppressure":{"value":99225.899539035},"fluiddensity":{},"fluidviscosity":{},"fluidph":{}},{"datetime":{"value":"2022-04-21T13:34:23"},"bottomtemperature":{},"bottomflow":{},"bottompressure":{},"toptemperature":{},"topflow":{"value":0.0019919783244550337},"toppressure":{"value":305616.551986054},"fluiddensity":{},"fluidviscosity":{},"fluidph":{}},{"datetime":{"value":"2022-04-21T13:35:23"},"bottomtemperature":{},"bottomflow":{},"bottompressure":{},"toptemperature":{},"topflow":{"value":0.0},"toppressure":{"value":301355.47706821247},"fluiddensity":{},"fluidviscosity":{},"fluidph":{}},{"datetime":{"value":"2022-04-21T13:36:23"},"bottomtemperature":{},"bottomflow":{},"bottompressure":{},"toptemperature":{},"topflow":{"value":0.0},"toppressure":{"value":295836.45368281053},"fluiddensity":{},"fluidviscosity":{},"fluidph":{}},{"datetime":{"value":"2022-04-21T13:37:23"},"bottomtemperature":{},"bottomflow":{},"bottompressure":{},"toptemperature":{},"topflow":{"value":0.008145695163007139},"toppressure":{"value":379560.8704067385},"fluiddensity":{},"fluidviscosity":{},"fluidph":{}},{"datetime":{"value":"2022-04-21T13:38:23"},"bottomtemperature":{},"bottomflow":{},"bottompressure":{},"toptemperature":{},"topflow":{"value":0.0005621609913852317},"toppressure":{"value":711410.5949297844},"fluiddensity":{},"fluidviscosity":{},"fluidph":{}},{"datetime":{"value":"2022-04-21T13:39:23"},"bottomtemperature":{},"bottomflow":{},"bottompressure":{},"toptemperature":{},"topflow":{"value":0.0030018210423672738},"toppressure":{"value":4373268.247066324},"fluiddensity":{},"fluidviscosity":{},"fluidph":{}},{"datetime":{"value":"2022-04-21T13:40:23"},"bottomtemperature":{},"bottomflow":{},"bottompressure":{},"toptemperature":{},"topflow":{"value":0.0069537026352920065},"toppressure":{"value":16824996.747291513},"fluiddensity":{},"fluidviscosity":{},"fluidph":{}},{"datetime":{"value":"2022-04-21T13:41:23"},"bottomtemperature":{},"bottomflow":{},"bottompressure":{},"toptemperature":{},"topflow":{"value":0.00969572876281872},"toppressure":{"value":38301755.352670126},"fluiddensity":{},"fluidviscosity":{},"fluidph":{}},{"datetime":{"value":"2022-04-21T13:42:23"},"bottomtemperature":{},"bottomflow":{},"bottompressure":{},"toptemperature":{},"topflow":{"value":0.009408552702624827},"toppressure":{"value":45515443.0858958},"fluiddensity":{},"fluidviscosity":{},"fluidph":{}},{"datetime":{"value":"2022-04-21T13:43:23"},"bottomtemperature":{},"bottomflow":{},"bottompressure":{},"toptemperature":{},"topflow":{"value":0.009400599131831715},"toppressure":{"value":44110648.69862142},"fluiddensity":{},"fluidviscosity":{},"fluidph":{}},{"datetime":{"value":"2022-04-21T13:44:23"},"bottomtemperature":{},"bottomflow":{},"bottompressure":{},"toptemperature":{},"topflow":{"value":0.009422927803935326},"toppressure":{"value":42716532.221962065},"fluiddensity":{},"fluidviscosity":{},"fluidph":{}},{"datetime":{"value":"2022-04-21T13:45:23"},"bottomtemperature":{},"bottomflow":{},"bottompressure":{},"toptemperature":{},"topflow":{"value":0.00951276403797555},"toppressure":{"value":42911162.94655002},"fluiddensity":{},"fluidviscosity":{},"fluidph":{}},{"datetime":{"value":"2022-04-21T13:46:23"},"bottomtemperature":{},"bottomflow":{},"bottompressure":{},"toptemperature":{},"topflow":{"value":0.009562441258830885},"toppressure":{"value":43044666.13195629},"fluiddensity":{},"fluidviscosity":{},"fluidph":{}},{"datetime":{"value":"2022-04-21T13:47:23"},"bottomtemperature":{},"bottomflow":{},"bottompressure":{},"toptemperature":{},"topflow":{"value":0.010379246902002122},"toppressure":{"value":43079425.24644548},"fluiddensity":{},"fluidviscosity":{},"fluidph":{}},{"datetime":{"value":"2022-04-21T13:48:23"},"bottomtemperature":{},"bottomflow":{},"bottompressure":{},"toptemperature":{},"topflow":{"value":0.010219034605083506},"toppressure":{"value":43881132.570573255},"fluiddensity":{},"fluidviscosity":{},"fluidph":{}},{"datetime":{"value":"2022-04-21T13:49:23"},"bottomtemperature":{},"bottomflow":{},"bottompressure":{},"toptemperature":{},"topflow":{"value":0.0028895257498169936},"toppressure":{"value":31135790.02676507},"fluiddensity":{},"fluidviscosity":{},"fluidph":{}},{"datetime":{"value":"2022-04-21T13:50:23"},"bottomtemperature":{},"bottomflow":{},"bottompressure":{},"toptemperature":{},"topflow":{"value":0.012648785289175771},"toppressure":{"value":41202158.422864124},"fluiddensity":{},"fluidviscosity":{},"fluidph":{}},{"datetime":{"value":"2022-04-21T13:51:23"},"bottomtemperature":{},"bottomflow":{},"bottompressure":{},"toptemperature":{},"topflow":{"value":0.01784246701707742},"toppressure":{"value":45950275.77811783},"fluiddensity":{},"fluidviscosity":{},"fluidph":{}},{"datetime":{"value":"2022-04-21T13:52:23"},"bottomtemperature":{},"bottomflow":{},"bottompressure":{},"toptemperature":{},"topflow":{"value":0.01921960824194366},"toppressure":{"value":47279003.18102717},"fluiddensity":{},"fluidviscosity":{},"fluidph":{}},{"datetime":{"value":"2022-04-21T13:53:23"},"bottomtemperature":{},"bottomflow":{},"bottompressure":{},"toptemperature":{},"topflow":{"value":0.019259832448331772},"toppressure":{"value":46988418.57888477},"fluiddensity":{},"fluidviscosity":{},"fluidph":{}},{"datetime":{"value":"2022-04-21T13:54:23"},"bottomtemperature":{},"bottomflow":{},"bottompressure":{},"toptemperature":{},"topflow":{"value":0.01919242267619999},"toppressure":{"value":46467960.125703484},"fluiddensity":{},"fluidviscosity":{},"fluidph":{}},{"datetime":{"value":"2022-04-21T13:55:23"},"bottomtemperature":{},"bottomflow":{},"bottompressure":{},"toptemperature":{},"topflow":{"value":0.01926563464341855},"toppressure":{"value":46155579.01242758},"fluiddensity":{},"fluidviscosity":{},"fluidph":{}},{"datetime":{"value":"2022-04-21T13:56:23"},"bottomtemperature":{},"bottomflow":{},"bottompressure":{},"toptemperature":{},"topflow":{"value":0.024804481785780253},"toppressure":{"value":47766666.83607119},"fluiddensity":{},"fluidviscosity":{},"fluidph":{}},{"datetime":{"value":"2022-04-21T13:57:23"},"bottomtemperature":{},"bottomflow":{},"bottompressure":{},"toptemperature":{},"topflow":{"value":0.029576624261647},"toppressure":{"value":49377831.99590908},"fluiddensity":{},"fluidviscosity":{},"fluidph":{}},{"datetime":{"value":"2022-04-21T13:58:23"},"bottomtemperature":{},"bottomflow":{},"bottompressure":{},"toptemperature":{},"topflow":{"value":0.030023523669735343},"toppressure":{"value":49596325.245652474},"fluiddensity":{},"fluidviscosity":{},"fluidph":{}},{"datetime":{"value":"2022-04-21T13:59:23"},"bottomtemperature":{},"bottomflow":{},"bottompressure":{},"toptemperature":{},"topflow":{"value":0.029979583450763566},"toppressure":{"value":49676077.59270163},"fluiddensity":{},"fluidviscosity":{},"fluidph":{}},{"datetime":{"value":"2022-04-21T14:00:23"},"bottomtemperature":{},"bottomflow":{},"bottompressure":{},"toptemperature":{},"topflow":{"value":0.030328008525384736},"toppressure":{"value":49082223.299042076},"fluiddensity":{},"fluidviscosity":{},"fluidph":{}},{"datetime":{"value":"2022-04-21T14:01:23"},"bottomtemperature":{},"bottomflow":{},"bottompressure":{},"toptemperature":{},"topflow":{"value":0.030476844608341075},"toppressure":{"value":48980279.83091718},"fluiddensity":{},"fluidviscosity":{},"fluidph":{}},{"datetime":{"value":"2022-04-21T14:02:23"},"bottomtemperature":{},"bottomflow":{},"bottompressure":{},"toptemperature":{},"topflow":{"value":0.03485310135764087},"toppressure":{"value":48827297.80704045},"fluiddensity":{},"fluidviscosity":{},"fluidph":{}},{"datetime":{"value":"2022-04-21T14:03:23"},"bottomtemperature":{},"bottomflow":{},"bottompressure":{},"toptemperature":{},"topflow":{"value":0.040268700749310965},"toppressure":{"value":48925282.99500515},"fluiddensity":{},"fluidviscosity":{},"fluidph":{}},{"datetime":{"value":"2022-04-21T14:04:23"},"bottomtemperature":{},"bottomflow":{},"bottompressure":{},"toptemperature":{},"topflow":{"value":0.04008019460219391},"toppressure":{"value":48601133.10559833},"fluiddensity":{},"fluidviscosity":{},"fluidph":{}},{"datetime":{"value":"2022-04-21T14:05:23"},"bottomtemperature":{},"bottomflow":{},"bottompressure":{},"toptemperature":{},"topflow":{"value":0.040097927153470346},"toppressure":{"value":48215251.92609647},"fluiddensity":{},"fluidviscosity":{},"fluidph":{}},{"datetime":{"value":"2022-04-21T14:06:23"},"bottomtemperature":{},"bottomflow":{},"bottompressure":{},"toptemperature":{},"topflow":{"value":0.040048119546208565},"toppressure":{"value":47523124.703267984},"fluiddensity":{},"fluidviscosity":{},"fluidph":{}},{"datetime":{"value":"2022-04-21T14:07:23"},"bottomtemperature":{},"bottomflow":{},"bottompressure":{},"toptemperature":{},"topflow":{"value":0.04352425373861913},"toppressure":{"value":47568627.918042175},"fluiddensity":{},"fluidviscosity":{},"fluidph":{}},{"datetime":{"value":"2022-04-21T14:08:23"},"bottomtemperature":{},"bottomflow":{},"bottompressure":{},"toptemperature":{},"topflow":{"value":0.048830458935282324},"toppressure":{"value":48077422.280490726},"fluiddensity":{},"fluidviscosity":{},"fluidph":{}},{"datetime":{"value":"2022-04-21T14:09:23"},"bottomtemperature":{},"bottomflow":{},"bottompressure":{},"toptemperature":{},"topflow":{"value":0.04886103454759355},"toppressure":{"value":47345710.64728364},"fluiddensity":{},"fluidviscosity":{},"fluidph":{}},{"datetime":{"value":"2022-04-21T14:10:23"},"bottomtemperature":{},"bottomflow":{},"bottompressure":{},"toptemperature":{},"topflow":{"value":0.04887456213726216},"toppressure":{"value":47040105.93129761},"fluiddensity":{},"fluidviscosity":{},"fluidph":{}},{"datetime":{"value":"2022-04-21T14:11:23"},"bottomtemperature":{},"bottomflow":{},"bottompressure":{},"toptemperature":{},"topflow":{"value":0.04885914394470011},"toppressure":{"value":47841921.962765336},"fluiddensity":{},"fluidviscosity":{},"fluidph":{}},{"datetime":{"value":"2022-04-21T14:12:23"},"bottomtemperature":{},"bottomflow":{},"bottompressure":{},"toptemperature":{},"topflow":{"value":0.04888254830465689},"toppressure":{"value":47618652.140084036},"fluiddensity":{},"fluidviscosity":{},"fluidph":{}},{"datetime":{"value":"2022-04-21T14:13:23"},"bottomtemperature":{},"bottomflow":{},"bottompressure":{},"toptemperature":{},"topflow":{"value":0.04888365658911167},"toppressure":{"value":47020715.80537094},"fluiddensity":{},"fluidviscosity":{},"fluidph":{}},{"datetime":{"value":"2022-04-21T14:14:23"},"bottomtemperature":{},"bottomflow":{},"bottompressure":{},"toptemperature":{},"topflow":{"value":0.04896022600629616},"toppressure":{"value":46708640.24475561},"fluiddensity":{},"fluidviscosity":{},"fluidph":{}},{"datetime":{"value":"2022-04-21T14:15:23"},"bottomtemperature":{},"bottomflow":{},"bottompressure":{},"toptemperature":{},"topflow":{"value":0.048981707166757885},"toppressure":{"value":46533725.88302677},"fluiddensity":{},"fluidviscosity":{},"fluidph":{}},{"datetime":{"value":"2022-04-21T14:16:23"},"bottomtemperature":{},"bottomflow":{},"bottompressure":{},"toptemperature":{},"topflow":{"value":0.04898982372055906},"toppressure":{"value":45970123.601015925},"fluiddensity":{},"fluidviscosity":{},"fluidph":{}},{"datetime":{"value":"2022-04-21T14:17:23"},"bottomtemperature":{},"bottomflow":{},"bottompressure":{},"toptemperature":{},"topflow":{"value":0.04894721996225333},"toppressure":{"value":45438417.04079173},"fluiddensity":{},"fluidviscosity":{},"fluidph":{}},{"datetime":{"value":"2022-04-21T14:18:23"},"bottomtemperature":{},"bottomflow":{},"bottompressure":{},"toptemperature":{},"topflow":{"value":0.05176796688267088},"toppressure":{"value":45444519.015906},"fluiddensity":{},"fluidviscosity":{},"fluidph":{}},{"datetime":{"value":"2022-04-21T14:19:23"},"bottomtemperature":{},"bottomflow":{},"bottompressure":{},"toptemperature":{},"topflow":{"value":0.057390163535352194},"toppressure":{"value":45770195.97913993},"fluiddensity":{},"fluidviscosity":{},"fluidph":{}},{"datetime":{"value":"2022-04-21T14:20:23"},"bottomtemperature":{},"bottomflow":{},"bottompressure":{},"toptemperature":{},"topflow":{"value":0.05831078935465483},"toppressure":{"value":45084353.21266865},"fluiddensity":{},"fluidviscosity":{},"fluidph":{}},{"datetime":{"value":"2022-04-21T14:21:23"},"bottomtemperature":{},"bottomflow":{},"bottompressure":{},"toptemperature":{},"topflow":{"value":0.05830619323382766},"toppressure":{"value":44476126.79743809},"fluiddensity":{},"fluidviscosity":{},"fluidph":{}},{"datetime":{"value":"2022-04-21T14:22:23"},"bottomtemperature":{},"bottomflow":{},"bottompressure":{},"toptemperature":{},"topflow":{"value":0.05825511435910305},"toppressure":{"value":44157065.353823915},"fluiddensity":{},"fluidviscosity":{},"fluidph":{}},{"datetime":{"value":"2022-04-21T14:23:23"},"bottomtemperature":{},"bottomflow":{},"bottompressure":{},"toptemperature":{},"topflow":{"value":0.05827864910546627},"toppressure":{"value":43825600.47167028},"fluiddensity":{},"fluidviscosity":{},"fluidph":{}},{"datetime":{"value":"2022-04-21T14:24:23"},"bottomtemperature":{},"bottomflow":{},"bottompressure":{},"toptemperature":{},"topflow":{"value":0.05819702721503205},"toppressure":{"value":43568896.36211307},"fluiddensity":{},"fluidviscosity":{},"fluidph":{}},{"datetime":{"value":"2022-04-21T14:25:23"},"bottomtemperature":{},"bottomflow":{},"bottompressure":{},"toptemperature":{},"topflow":{"value":0.05829703358877494},"toppressure":{"value":43275348.62311268},"fluiddensity":{},"fluidviscosity":{},"fluidph":{}},{"datetime":{"value":"2022-04-21T14:26:23"},"bottomtemperature":{},"bottomflow":{},"bottompressure":{},"toptemperature":{},"topflow":{"value":0.0582353282219251},"toppressure":{"value":43012349.600149706},"fluiddensity":{},"fluidviscosity":{},"fluidph":{}},{"datetime":{"value":"2022-04-21T14:27:23"},"bottomtemperature":{},"bottomflow":{},"bottompressure":{},"toptemperature":{},"topflow":{"value":0.05829214409853327},"toppressure":{"value":42816745.22091978},"fluiddensity":{},"fluidviscosity":{},"fluidph":{}},{"datetime":{"value":"2022-04-21T14:28:23"},"bottomtemperature":{},"bottomflow":{},"bottompressure":{},"toptemperature":{},"topflow":{"value":0.058179718419576545},"toppressure":{"value":42709603.680361345},"fluiddensity":{},"fluidviscosity":{},"fluidph":{}},{"datetime":{"value":"2022-04-21T14:29:23"},"bottomtemperature":{},"bottomflow":{},"bottompressure":{},"toptemperature":{},"topflow":{"value":0.05826257898087199},"toppressure":{"value":42586569.72424945},"fluiddensity":{},"fluidviscosity":{},"fluidph":{}},{"datetime":{"value":"2022-04-21T14:30:23"},"bottomtemperature":{},"bottomflow":{},"bottompressure":{},"toptemperature":{},"topflow":{"value":0.058277801593824376},"toppressure":{"value":42419280.7342581},"fluiddensity":{},"fluidviscosity":{},"fluidph":{}},{"datetime":{"value":"2022-04-21T14:31:23"},"bottomtemperature":{},"bottomflow":{},"bottompressure":{},"toptemperature":{},"topflow":{"value":0.05838556595875071},"toppressure":{"value":42165409.10590825},"fluiddensity":{},"fluidviscosity":{},"fluidph":{}},{"datetime":{"value":"2022-04-21T14:32:23"},"bottomtemperature":{},"bottomflow":{},"bottompressure":{},"toptemperature":{},"topflow":{"value":0.05856980195105672},"toppressure":{"value":42007599.487889685},"fluiddensity":{},"fluidviscosity":{},"fluidph":{}},{"datetime":{"value":"2022-04-21T14:33:23"},"bottomtemperature":{},"bottomflow":{},"bottompressure":{},"toptemperature":{},"topflow":{"value":0.058739565052247394},"toppressure":{"value":41815598.30881952},"fluiddensity":{},"fluidviscosity":{},"fluidph":{}},{"datetime":{"value":"2022-04-21T14:34:23"},"bottomtemperature":{},"bottomflow":{},"bottompressure":{},"toptemperature":{},"topflow":{"value":0.05884159241529017},"toppressure":{"value":41580938.57692039},"fluiddensity":{},"fluidviscosity":{},"fluidph":{}},{"datetime":{"value":"2022-04-21T14:35:23"},"bottomtemperature":{},"bottomflow":{},"bottompressure":{},"toptemperature":{},"topflow":{"value":0.058876927131436614},"toppressure":{"value":41330505.019293204},"fluiddensity":{},"fluidviscosity":{},"fluidph":{}},{"datetime":{"value":"2022-04-21T14:36:23"},"bottomtemperature":{},"bottomflow":{},"bottompressure":{},"toptemperature":{},"topflow":{"value":0.058889802789073006},"toppressure":{"value":41287828.769920535},"fluiddensity":{},"fluidviscosity":{},"fluidph":{}},{"datetime":{"value":"2022-04-21T14:37:23"},"bottomtemperature":{},"bottomflow":{},"bottompressure":{},"toptemperature":{},"topflow":{"value":0.058911316546136336},"toppressure":{"value":40982729.09490599},"fluiddensity":{},"fluidviscosity":{},"fluidph":{}},{"datetime":{"value":"2022-04-21T14:38:23"},"bottomtemperature":{},"bottomflow":{},"bottompressure":{},"toptemperature":{},"topflow":{"value":0.058991210816685166},"toppressure":{"value":40671387.5961168},"fluiddensity":{},"fluidviscosity":{},"fluidph":{}},{"datetime":{"value":"2022-04-21T14:39:23"},"bottomtemperature":{},"bottomflow":{},"bottompressure":{},"toptemperature":{},"topflow":{"value":0.05894652087587634},"toppressure":{"value":40246589.41874202},"fluiddensity":{},"fluidviscosity":{},"fluidph":{}},{"datetime":{"value":"2022-04-21T14:40:23"},"bottomtemperature":{},"bottomflow":{},"bottompressure":{},"toptemperature":{},"topflow":{"value":0.05895356174182433},"toppressure":{"value":39880950.097517386},"fluiddensity":{},"fluidviscosity":{},"fluidph":{}},{"datetime":{"value":"2022-04-21T14:41:23"},"bottomtemperature":{},"bottomflow":{},"bottompressure":{},"toptemperature":{},"topflow":{"value":0.05897716168139078},"toppressure":{"value":39610971.28192451},"fluiddensity":{},"fluidviscosity":{},"fluidph":{}},{"datetime":{"value":"2022-04-21T14:42:23"},"bottomtemperature":{},"bottomflow":{},"bottompressure":{},"toptemperature":{},"topflow":{"value":0.05896288436988511},"toppressure":{"value":39319239.6219943},"fluiddensity":{},"fluidviscosity":{},"fluidph":{}},{"datetime":{"value":"2022-04-21T14:43:23"},"bottomtemperature":{},"bottomflow":{},"bottompressure":{},"toptemperature":{},"topflow":{"value":0.0589663722062575},"toppressure":{"value":39243650.0995716},"fluiddensity":{},"fluidviscosity":{},"fluidph":{}},{"datetime":{"value":"2022-04-21T14:44:23"},"bottomtemperature":{},"bottomflow":{},"bottompressure":{},"toptemperature":{},"topflow":{"value":0.05897204401493783},"toppressure":{"value":39375540.831072986},"fluiddensity":{},"fluidviscosity":{},"fluidph":{}},{"datetime":{"value":"2022-04-21T14:45:23"},"bottomtemperature":{},"bottomflow":{},"bottompressure":{},"toptemperature":{},"topflow":{"value":0.058910338648088},"toppressure":{"value":39572442.803624876},"fluiddensity":{},"fluidviscosity":{},"fluidph":{}},{"datetime":{"value":"2022-04-21T14:46:23"},"bottomtemperature":{},"bottomflow":{},"bottompressure":{},"toptemperature":{},"topflow":{"value":0.05887666635862372},"toppressure":{"value":39593999.60702992},"fluiddensity":{},"fluidviscosity":{},"fluidph":{}},{"datetime":{"value":"2022-04-21T14:47:23"},"bottomtemperature":{},"bottomflow":{},"bottompressure":{},"toptemperature":{},"topflow":{"value":0.058729623088756},"toppressure":{"value":39543551.35741473},"fluiddensity":{},"fluidviscosity":{},"fluidph":{}},{"datetime":{"value":"2022-04-21T14:48:23"},"bottomtemperature":{},"bottomflow":{},"bottompressure":{},"toptemperature":{},"topflow":{"value":0.05858779527514605},"toppressure":{"value":39441334.167425424},"fluiddensity":{},"fluidviscosity":{},"fluidph":{}},{"datetime":{"value":"2022-04-21T14:49:23"},"bottomtemperature":{},"bottomflow":{},"bottompressure":{},"toptemperature":{},"topflow":{"value":0.058238848654899096},"toppressure":{"value":39128648.30587731},"fluiddensity":{},"fluidviscosity":{},"fluidph":{}},{"datetime":{"value":"2022-04-21T14:50:23"},"bottomtemperature":{},"bottomflow":{},"bottompressure":{},"toptemperature":{},"topflow":{"value":0.05810490921887905},"toppressure":{"value":38940264.57613196},"fluiddensity":{},"fluidviscosity":{},"fluidph":{}},{"datetime":{"value":"2022-04-21T14:51:23"},"bottomtemperature":{},"bottomflow":{},"bottompressure":{},"toptemperature":{},"topflow":{"value":0.05793543948710288},"toppressure":{"value":38742176.13076308},"fluiddensity":{},"fluidviscosity":{},"fluidph":{}},{"datetime":{"value":"2022-04-21T14:52:23"},"bottomtemperature":{},"bottomflow":{},"bottompressure":{},"toptemperature":{},"topflow":{"value":0.05792272681247453},"toppressure":{"value":38561202.54141516},"fluiddensity":{},"fluidviscosity":{},"fluidph":{}},{"datetime":{"value":"2022-04-21T14:53:23"},"bottomtemperature":{},"bottomflow":{},"bottompressure":{},"toptemperature":{},"topflow":{"value":0.05801086802323099},"toppressure":{"value":38346548.40744346},"fluiddensity":{},"fluidviscosity":{},"fluidph":{}},{"datetime":{"value":"2022-04-21T14:54:23"},"bottomtemperature":{},"bottomflow":{},"bottompressure":{},"toptemperature":{},"topflow":{"value":0.06259466733498872},"toppressure":{"value":38832659.363145776},"fluiddensity":{},"fluidviscosity":{},"fluidph":{}},{"datetime":{"value":"2022-04-21T14:55:23"},"bottomtemperature":{},"bottomflow":{},"bottompressure":{},"toptemperature":{},"topflow":{"value":0.06787867424595477},"toppressure":{"value":39346717.06839689},"fluiddensity":{},"fluidviscosity":{},"fluidph":{}},{"datetime":{"value":"2022-04-21T14:56:23"},"bottomtemperature":{},"bottomflow":{},"bottompressure":{},"toptemperature":{},"topflow":{"value":0.06844181313538834},"toppressure":{"value":39133334.90223257},"fluiddensity":{},"fluidviscosity":{},"fluidph":{}},{"datetime":{"value":"2022-04-21T14:57:23"},"bottomtemperature":{},"bottomflow":{},"bottompressure":{},"toptemperature":{},"topflow":{"value":0.06842786178989878},"toppressure":{"value":38880960.815166116},"fluiddensity":{},"fluidviscosity":{},"fluidph":{}},{"datetime":{"value":"2022-04-21T14:58:23"},"bottomtemperature":{},"bottomflow":{},"bottompressure":{},"toptemperature":{},"topflow":{"value":0.06834040510777617},"toppressure":{"value":38642122.285786144},"fluiddensity":{},"fluidviscosity":{},"fluidph":{}},{"datetime":{"value":"2022-04-21T14:59:23"},"bottomtemperature":{},"bottomflow":{},"bottompressure":{},"toptemperature":{},"topflow":{"value":0.06829095606313211},"toppressure":{"value":38572440.306322135},"fluiddensity":{},"fluidviscosity":{},"fluidph":{}},{"datetime":{"value":"2022-04-21T15:00:23"},"bottomtemperature":{},"bottomflow":{},"bottompressure":{},"toptemperature":{},"topflow":{"value":0.06819215576364883},"toppressure":{"value":38480794.502947725},"fluiddensity":{},"fluidviscosity":{},"fluidph":{}},{"datetime":{"value":"2022-04-21T15:01:23"},"bottomtemperature":{},"bottomflow":{},"bottompressure":{},"toptemperature":{},"topflow":{"value":0.06820376015382239},"toppressure":{"value":38489734.93472567},"fluiddensity":{},"fluidviscosity":{},"fluidph":{}},{"datetime":{"value":"2022-04-21T15:02:23"},"bottomtemperature":{},"bottomflow":{},"bottompressure":{},"toptemperature":{},"topflow":{"value":0.06818909168309738},"toppressure":{"value":38220591.41897846},"fluiddensity":{},"fluidviscosity":{},"fluidph":{}},{"datetime":{"value":"2022-04-21T15:03:23"},"bottomtemperature":{},"bottomflow":{},"bottompressure":{},"toptemperature":{},"topflow":{"value":0.06817025084736615},"toppressure":{"value":38382272.098477505},"fluiddensity":{},"fluidviscosity":{},"fluidph":{}},{"datetime":{"value":"2022-04-21T15:04:23"},"bottomtemperature":{},"bottomflow":{},"bottompressure":{},"toptemperature":{},"topflow":{"value":0.06822674075795822},"toppressure":{"value":38074154.12854665},"fluiddensity":{},"fluidviscosity":{},"fluidph":{}},{"datetime":{"value":"2022-04-21T15:05:23"},"bottomtemperature":{},"bottomflow":{},"bottompressure":{},"toptemperature":{},"topflow":{"value":0.068299431179551},"toppressure":{"value":37998349.83443435},"fluiddensity":{},"fluidviscosity":{},"fluidph":{}},{"datetime":{"value":"2022-04-21T15:06:23"},"bottomtemperature":{},"bottomflow":{},"bottompressure":{},"toptemperature":{},"topflow":{"value":0.06811059906641782},"toppressure":{"value":37957493.68607363},"fluiddensity":{},"fluidviscosity":{},"fluidph":{}},{"datetime":{"value":"2022-04-21T15:07:23"},"bottomtemperature":{},"bottomflow":{},"bottompressure":{},"toptemperature":{},"topflow":{"value":0.06781126447382299},"toppressure":{"value":37753595.37347433},"fluiddensity":{},"fluidviscosity":{},"fluidph":{}},{"datetime":{"value":"2022-04-21T15:08:23"},"bottomtemperature":{},"bottomflow":{},"bottompressure":{},"toptemperature":{},"topflow":{"value":0.06769000511582966},"toppressure":{"value":37600036.02858717},"fluiddensity":{},"fluidviscosity":{},"fluidph":{}},{"datetime":{"value":"2022-04-21T15:09:23"},"bottomtemperature":{},"bottomflow":{},"bottompressure":{},"toptemperature":{},"topflow":{"value":0.06739018157421064},"toppressure":{"value":37323990.28622958},"fluiddensity":{},"fluidviscosity":{},"fluidph":{}},{"datetime":{"value":"2022-04-21T15:10:23"},"bottomtemperature":{},"bottomflow":{},"bottompressure":{},"toptemperature":{},"topflow":{"value":0.06773107683385965},"toppressure":{"value":37207427.05983435},"fluiddensity":{},"fluidviscosity":{},"fluidph":{}},{"datetime":{"value":"2022-04-21T15:11:23"},"bottomtemperature":{},"bottomflow":{},"bottompressure":{},"toptemperature":{},"topflow":{"value":0.06751626522924242},"toppressure":{"value":36900544.97514772},"fluiddensity":{},"fluidviscosity":{},"fluidph":{}},{"datetime":{"value":"2022-04-21T15:12:23"},"bottomtemperature":{},"bottomflow":{},"bottompressure":{},"toptemperature":{},"topflow":{"value":0.0675423099139297},"toppressure":{"value":36590537.15224366},"fluiddensity":{},"fluidviscosity":{},"fluidph":{}},{"datetime":{"value":"2022-04-21T15:13:23"},"bottomtemperature":{},"bottomflow":{},"bottompressure":{},"toptemperature":{},"topflow":{"value":0.06752894530726915},"toppressure":{"value":36644791.19297032},"fluiddensity":{},"fluidviscosity":{},"fluidph":{}},{"datetime":{"value":"2022-04-21T15:14:23"},"bottomtemperature":{},"bottomflow":{},"bottompressure":{},"toptemperature":{},"topflow":{"value":0.06750739895360419},"toppressure":{"value":36405618.84242489},"fluiddensity":{},"fluidviscosity":{},"fluidph":{}},{"datetime":{"value":"2022-04-21T15:15:23"},"bottomtemperature":{},"bottomflow":{},"bottompressure":{},"toptemperature":{},"topflow":{"value":0.06745306041871847},"toppressure":{"value":36189188.50406266},"fluiddensity":{},"fluidviscosity":{},"fluidph":{}},{"datetime":{"value":"2022-04-21T15:16:23"},"bottomtemperature":{},"bottomflow":{},"bottompressure":{},"toptemperature":{},"topflow":{"value":0.06757063636072975},"toppressure":{"value":36280341.56211608},"fluiddensity":{},"fluidviscosity":{},"fluidph":{}},{"datetime":{"value":"2022-04-21T15:17:23"},"bottomtemperature":{},"bottomflow":{},"bottompressure":{},"toptemperature":{},"topflow":{"value":0.06747023882776754},"toppressure":{"value":35997645.251789175},"fluiddensity":{},"fluidviscosity":{},"fluidph":{}},{"datetime":{"value":"2022-04-21T15:18:23"},"bottomtemperature":{},"bottomflow":{},"bottompressure":{},"toptemperature":{},"topflow":{"value":0.06750723597059613},"toppressure":{"value":35574649.01923214},"fluiddensity":{},"fluidviscosity":{},"fluidph":{}},{"datetime":{"value":"2022-04-21T15:19:23"},"bottomtemperature":{},"bottomflow":{},"bottompressure":{},"toptemperature":{},"topflow":{"value":0.06748526586111026},"toppressure":{"value":35335399.79214292},"fluiddensity":{},"fluidviscosity":{},"fluidph":{}},{"datetime":{"value":"2022-04-21T15:20:23"},"bottomtemperature":{},"bottomflow":{},"bottompressure":{},"toptemperature":{},"topflow":{"value":0.06740129701536002},"toppressure":{"value":35356011.78397399},"fluiddensity":{},"fluidviscosity":{},"fluidph":{}},{"datetime":{"value":"2022-04-21T15:21:23"},"bottomtemperature":{},"bottomflow":{},"bottompressure":{},"toptemperature":{},"topflow":{"value":0.06747258578308354},"toppressure":{"value":35323498.63667203},"fluiddensity":{},"fluidviscosity":{},"fluidph":{}},{"datetime":{"value":"2022-04-21T15:22:23"},"bottomtemperature":{},"bottomflow":{},"bottompressure":{},"toptemperature":{},"topflow":{"value":0.06738398821990453},"toppressure":{"value":35446722.88808513},"fluiddensity":{},"fluidviscosity":{},"fluidph":{}},{"datetime":{"value":"2022-04-21T15:23:23"},"bottomtemperature":{},"bottomflow":{},"bottompressure":{},"toptemperature":{},"topflow":{"value":0.06745263666289752},"toppressure":{"value":35542359.951542094},"fluiddensity":{},"fluidviscosity":{},"fluidph":{}},{"datetime":{"value":"2022-04-21T15:24:23"},"bottomtemperature":{},"bottomflow":{},"bottompressure":{},"toptemperature":{},"topflow":{"value":0.06747754046652843},"toppressure":{"value":35514659.80447903},"fluiddensity":{},"fluidviscosity":{},"fluidph":{}},{"datetime":{"value":"2022-04-21T15:25:23"},"bottomtemperature":{},"bottomflow":{},"bottompressure":{},"toptemperature":{},"topflow":{"value":0.057120459253621865},"toppressure":{"value":34047196.89976866},"fluiddensity":{},"fluidviscosity":{},"fluidph":{}},{"datetime":{"value":"2022-04-21T15:26:23"},"bottomtemperature":{},"bottomflow":{},"bottompressure":{},"toptemperature":{},"topflow":{"value":0.03893383731673433},"toppressure":{"value":31484729.786182836},"fluiddensity":{},"fluidviscosity":{},"fluidph":{}},{"datetime":{"value":"2022-04-21T15:27:23"},"bottomtemperature":{},"bottomflow":{},"bottompressure":{},"toptemperature":{},"topflow":{"value":0.03884497898074244},"toppressure":{"value":31536842.2003826},"fluiddensity":{},"fluidviscosity":{},"fluidph":{}},{"datetime":{"value":"2022-04-21T15:28:23"},"bottomtemperature":{},"bottomflow":{},"bottompressure":{},"toptemperature":{},"topflow":{"value":0.03887141482464905},"toppressure":{"value":31587395.02048337},"fluiddensity":{},"fluidviscosity":{},"fluidph":{}},{"datetime":{"value":"2022-04-21T15:29:23"},"bottomtemperature":{},"bottomflow":{},"bottompressure":{},"toptemperature":{},"topflow":{"value":0.03885818060439494},"toppressure":{"value":31574898.73254573},"fluiddensity":{},"fluidviscosity":{},"fluidph":{}},{"datetime":{"value":"2022-04-21T15:30:23"},"bottomtemperature":{},"bottomflow":{},"bottompressure":{},"toptemperature":{},"topflow":{"value":0.03893360914052305},"toppressure":{"value":31606515.561399996},"fluiddensity":{},"fluidviscosity":{},"fluidph":{}},{"datetime":{"value":"2022-04-21T15:31:23"},"bottomtemperature":{},"bottomflow":{},"bottompressure":{},"toptemperature":{},"topflow":{"value":0.03892050530667539},"toppressure":{"value":31649814.29244333},"fluiddensity":{},"fluidviscosity":{},"fluidph":{}},{"datetime":{"value":"2022-04-21T15:32:23"},"bottomtemperature":{},"bottomflow":{},"bottompressure":{},"toptemperature":{},"topflow":{"value":0.03886802477808149},"toppressure":{"value":31671253.54023659},"fluiddensity":{},"fluidviscosity":{},"fluidph":{}},{"datetime":{"value":"2022-04-21T15:33:23"},"bottomtemperature":{},"bottomflow":{},"bottompressure":{},"toptemperature":{},"topflow":{"value":0.03881792380140521},"toppressure":{"value":31721731.896958623},"fluiddensity":{},"fluidviscosity":{},"fluidph":{}},{"datetime":{"value":"2022-04-21T15:34:23"},"bottomtemperature":{},"bottomflow":{},"bottompressure":{},"toptemperature":{},"topflow":{"value":0.03879673601035799},"toppressure":{"value":31750022.80980881},"fluiddensity":{},"fluidviscosity":{},"fluidph":{}},{"datetime":{"value":"2022-04-21T15:35:23"},"bottomtemperature":{},"bottomflow":{},"bottompressure":{},"toptemperature":{},"topflow":{"value":0.034067490662211465},"toppressure":{"value":30976565.604550585},"fluiddensity":{},"fluidviscosity":{},"fluidph":{}},{"datetime":{"value":"2022-04-21T15:36:23"},"bottomtemperature":{},"bottomflow":{},"bottompressure":{},"toptemperature":{},"topflow":{"value":0.030635557461585576},"toppressure":{"value":30278745.26571512},"fluiddensity":{},"fluidviscosity":{},"fluidph":{}},{"datetime":{"value":"2022-04-21T15:37:23"},"bottomtemperature":{},"bottomflow":{},"bottompressure":{},"toptemperature":{},"topflow":{"value":0.030634872932951744},"toppressure":{"value":30315887.553061597},"fluiddensity":{},"fluidviscosity":{},"fluidph":{}},{"datetime":{"value":"2022-04-21T15:38:23"},"bottomtemperature":{},"bottomflow":{},"bottompressure":{},"toptemperature":{},"topflow":{"value":0.030507452817253904},"toppressure":{"value":30335917.167726908},"fluiddensity":{},"fluidviscosity":{},"fluidph":{}},{"datetime":{"value":"2022-04-21T15:39:23"},"bottomtemperature":{},"bottomflow":{},"bottompressure":{},"toptemperature":{},"topflow":{"value":0.030473747931188018},"toppressure":{"value":30349080.408519737},"fluiddensity":{},"fluidviscosity":{},"fluidph":{}},{"datetime":{"value":"2022-04-21T15:40:23"},"bottomtemperature":{},"bottomflow":{},"bottompressure":{},"toptemperature":{},"topflow":{"value":0.030463936354103074},"toppressure":{"value":30373259.288122173},"fluiddensity":{},"fluidviscosity":{},"fluidph":{}},{"datetime":{"value":"2022-04-21T15:41:23"},"bottomtemperature":{},"bottomflow":{},"bottompressure":{},"toptemperature":{},"topflow":{"value":0.030485417514564794},"toppressure":{"value":30391664.95762045},"fluiddensity":{},"fluidviscosity":{},"fluidph":{}},{"datetime":{"value":"2022-04-21T15:42:23"},"bottomtemperature":{},"bottomflow":{},"bottompressure":{},"toptemperature":{},"topflow":{"value":0.03050719204444102},"toppressure":{"value":30444497.414306536},"fluiddensity":{},"fluidviscosity":{},"fluidph":{}},{"datetime":{"value":"2022-04-21T15:43:23"},"bottomtemperature":{},"bottomflow":{},"bottompressure":{},"toptemperature":{},"topflow":{"value":0.03049786941638024},"toppressure":{"value":30456547.841272756},"fluiddensity":{},"fluidviscosity":{},"fluidph":{}},{"datetime":{"value":"2022-04-21T15:44:23"},"bottomtemperature":{},"bottomflow":{},"bottompressure":{},"toptemperature":{},"topflow":{"value":0.030520850020516077},"toppressure":{"value":30515399.650898244},"fluiddensity":{},"fluidviscosity":{},"fluidph":{}},{"datetime":{"value":"2022-04-21T15:45:23"},"bottomtemperature":{},"bottomflow":{},"bottompressure":{},"toptemperature":{},"topflow":{"value":0.023643814592213402},"toppressure":{"value":29327979.953909587},"fluiddensity":{},"fluidviscosity":{},"fluidph":{}},{"datetime":{"value":"2022-04-21T15:46:23"},"bottomtemperature":{},"bottomflow":{},"bottompressure":{},"toptemperature":{},"topflow":{"value":0.02047258901127318},"toppressure":{"value":28574767.82448199},"fluiddensity":{},"fluidviscosity":{},"fluidph":{}},{"datetime":{"value":"2022-04-21T15:47:23"},"bottomtemperature":{},"bottomflow":{},"bottompressure":{},"toptemperature":{},"topflow":{"value":0.020472263045257066},"toppressure":{"value":28536945.36932886},"fluiddensity":{},"fluidviscosity":{},"fluidph":{}},{"datetime":{"value":"2022-04-21T15:48:23"},"bottomtemperature":{},"bottomflow":{},"bottompressure":{},"toptemperature":{},"topflow":{"value":0.020445957587756903},"toppressure":{"value":28508827.74471189},"fluiddensity":{},"fluidviscosity":{},"fluidph":{}},{"datetime":{"value":"2022-04-21T15:49:23"},"bottomtemperature":{},"bottomflow":{},"bottompressure":{},"toptemperature":{},"topflow":{"value":0.020425226149132236},"toppressure":{"value":28509849.43282964},"fluiddensity":{},"fluidviscosity":{},"fluidph":{}},{"datetime":{"value":"2022-04-21T15:50:23"},"bottomtemperature":{},"bottomflow":{},"bottompressure":{},"toptemperature":{},"topflow":{"value":0.012969959604850053},"toppressure":{"value":27300963.943232164},"fluiddensity":{},"fluidviscosity":{},"fluidph":{}},{"datetime":{"value":"2022-04-21T15:51:23"},"bottomtemperature":{},"bottomflow":{},"bottompressure":{},"toptemperature":{},"topflow":{"value":0.010168216503171783},"toppressure":{"value":26616683.643675424},"fluiddensity":{},"fluidviscosity":{},"fluidph":{}},{"datetime":{"value":"2022-04-21T15:52:23"},"bottomtemperature":{},"bottomflow":{},"bottompressure":{},"toptemperature":{},"topflow":{"value":0.01022053404875762},"toppressure":{"value":26521572.07563657},"fluiddensity":{},"fluidviscosity":{},"fluidph":{}},{"datetime":{"value":"2022-04-21T15:53:23"},"bottomtemperature":{},"bottomflow":{},"bottompressure":{},"toptemperature":{},"topflow":{"value":0.010237321298587341},"toppressure":{"value":26463796.767449286},"fluiddensity":{},"fluidviscosity":{},"fluidph":{}},{"datetime":{"value":"2022-04-21T15:54:23"},"bottomtemperature":{},"bottomflow":{},"bottompressure":{},"toptemperature":{},"topflow":{"value":0.010243384266487007},"toppressure":{"value":26417539.151314948},"fluiddensity":{},"fluidviscosity":{},"fluidph":{}},{"datetime":{"value":"2022-04-21T15:55:23"},"bottomtemperature":{},"bottomflow":{},"bottompressure":{},"toptemperature":{},"topflow":{"value":0.007014951649719286},"toppressure":{"value":26008942.38953283},"fluiddensity":{},"fluidviscosity":{},"fluidph":{}},{"datetime":{"value":"2022-04-21T15:56:23"},"bottomtemperature":{},"bottomflow":{},"bottompressure":{},"toptemperature":{},"topflow":{"value":0.0},"toppressure":{"value":24721016.896226875},"fluiddensity":{},"fluidviscosity":{},"fluidph":{}},{"datetime":{"value":"2022-04-21T15:57:23"},"bottomtemperature":{},"bottomflow":{},"bottompressure":{},"toptemperature":{},"topflow":{"value":0.0},"toppressure":{"value":24448909.3243207},"fluiddensity":{},"fluidviscosity":{},"fluidph":{}},{"datetime":{"value":"2022-04-21T15:58:23"},"bottomtemperature":{},"bottomflow":{},"bottompressure":{},"toptemperature":{},"topflow":{"value":0.0},"toppressure":{"value":24267718.43520553},"fluiddensity":{},"fluidviscosity":{},"fluidph":{}},{"datetime":{"value":"2022-04-21T15:59:23"},"bottomtemperature":{},"bottomflow":{},"bottompressure":{},"toptemperature":{},"topflow":{"value":0.0022178401770184264},"toppressure":{"value":24118379.02651772},"fluiddensity":{},"fluidviscosity":{},"fluidph":{}},{"datetime":{"value":"2022-04-21T16:00:23"},"bottomtemperature":{},"bottomflow":{},"bottompressure":{},"toptemperature":{},"topflow":{"value":0.0017856744328583081},"toppressure":{"value":23985501.540335517},"fluiddensity":{},"fluidviscosity":{},"fluidph":{}},{"datetime":{"value":"2022-04-21T16:01:23"},"bottomtemperature":{},"bottomflow":{},"bottompressure":{},"toptemperature":{},"topflow":{"value":0.001574546244223138},"toppressure":{"value":23862737.284146287},"fluiddensity":{},"fluidviscosity":{},"fluidph":{}},{"datetime":{"value":"2022-04-21T16:02:23"},"bottomtemperature":{},"bottomflow":{},"bottompressure":{},"toptemperature":{},"topflow":{"value":0.0018754128770936986},"toppressure":{"value":23749991.455037292},"fluiddensity":{},"fluidviscosity":{},"fluidph":{}},{"datetime":{"value":"2022-04-21T16:03:23"},"bottomtemperature":{},"bottomflow":{},"bottompressure":{},"toptemperature":{},"topflow":{"value":0.0017410822818543074},"toppressure":{"value":23639309.111872572},"fluiddensity":{},"fluidviscosity":{},"fluidph":{}},{"datetime":{"value":"2022-04-21T16:04:23"},"bottomtemperature":{},"bottomflow":{},"bottompressure":{},"toptemperature":{},"topflow":{"value":0.0016631438074021392},"toppressure":{"value":23540315.79547945},"fluiddensity":{},"fluidviscosity":{},"fluidph":{}},{"datetime":{"value":"2022-04-21T16:05:23"},"bottomtemperature":{},"bottomflow":{},"bottompressure":{},"toptemperature":{},"topflow":{"value":0.0013543887969416897},"toppressure":{"value":23440379.391201682},"fluiddensity":{},"fluidviscosity":{},"fluidph":{}},{"datetime":{"value":"2022-04-21T16:06:23"},"bottomtemperature":{},"bottomflow":{},"bottompressure":{},"toptemperature":{},"topflow":{"value":0.0016421841925661946},"toppressure":{"value":23347629.5073599},"fluiddensity":{},"fluidviscosity":{},"fluidph":{}},{"datetime":{"value":"2022-04-21T16:07:23"},"bottomtemperature":{},"bottomflow":{},"bottompressure":{},"toptemperature":{},"topflow":{"value":0.0020141440135505897},"toppressure":{"value":23261591.09517683},"fluiddensity":{},"fluidviscosity":{},"fluidph":{}},{"datetime":{"value":"2022-04-21T16:08:23"},"bottomtemperature":{},"bottomflow":{},"bottompressure":{},"toptemperature":{},"topflow":{"value":0.004327198863875073},"toppressure":{"value":23177776.472045023},"fluiddensity":{},"fluidviscosity":{},"fluidph":{}},{"datetime":{"value":"2022-04-21T16:09:23"},"bottomtemperature":{},"bottomflow":{},"bottompressure":{},"toptemperature":{},"topflow":{"value":0.004989170649393529},"toppressure":{"value":23100073.476687696},"fluiddensity":{},"fluidviscosity":{},"fluidph":{}},{"datetime":{"value":"2022-04-21T16:10:23"},"bottomtemperature":{},"bottomflow":{},"bottompressure":{},"toptemperature":{},"topflow":{"value":0.006750462824246727},"toppressure":{"value":23021314.20451354},"fluiddensity":{},"fluidviscosity":{},"fluidph":{}},{"datetime":{"value":"2022-04-21T16:11:23"},"bottomtemperature":{},"bottomflow":{},"bottompressure":{},"toptemperature":{},"topflow":{"value":0.006745931896622781},"toppressure":{"value":22945517.264809035},"fluiddensity":{},"fluidviscosity":{},"fluidph":{}},{"datetime":{"value":"2022-04-21T16:12:23"},"bottomtemperature":{},"bottomflow":{},"bottompressure":{},"toptemperature":{},"topflow":{"value":0.006694364072874003},"toppressure":{"value":22873114.614118394},"fluiddensity":{},"fluidviscosity":{},"fluidph":{}},{"datetime":{"value":"2022-04-21T16:13:23"},"bottomtemperature":{},"bottomflow":{},"bottompressure":{},"toptemperature":{},"topflow":{"value":0.006714019823645504},"toppressure":{"value":22802710.17900301},"fluiddensity":{},"fluidviscosity":{},"fluidph":{}},{"datetime":{"value":"2022-04-21T16:14:23"},"bottomtemperature":{},"bottomflow":{},"bottompressure":{},"toptemperature":{},"topflow":{"value":0.006685758570048669},"toppressure":{"value":22735064.221366744},"fluiddensity":{},"fluidviscosity":{},"fluidph":{}},{"datetime":{"value":"2022-04-21T16:15:23"},"bottomtemperature":{},"bottomflow":{},"bottompressure":{},"toptemperature":{},"topflow":{"value":0.004325471243989684},"toppressure":{"value":22670637.540821794},"fluiddensity":{},"fluidviscosity":{},"fluidph":{}},{"datetime":{"value":"2022-04-21T16:16:23"},"bottomtemperature":{},"bottomflow":{},"bottompressure":{},"toptemperature":{},"topflow":{"value":0.0014495708736461358},"toppressure":{"value":22608330.308667798},"fluiddensity":{},"fluidviscosity":{},"fluidph":{}},{"datetime":{"value":"2022-04-21T16:17:23"},"bottomtemperature":{},"bottomflow":{},"bottompressure":{},"toptemperature":{},"topflow":{"value":0.0006811711838674004},"toppressure":{"value":22546069.960863367},"fluiddensity":{},"fluidviscosity":{},"fluidph":{}},{"datetime":{"value":"2022-04-21T16:18:23"},"bottomtemperature":{},"bottomflow":{},"bottompressure":{},"toptemperature":{},"topflow":{"value":0.00036990623508289513},"toppressure":{"value":22483580.70711691},"fluiddensity":{},"fluidviscosity":{},"fluidph":{}},{"datetime":{"value":"2022-04-21T16:19:23"},"bottomtemperature":{},"bottomflow":{},"bottompressure":{},"toptemperature":{},"topflow":{"value":0.0007607720850017351},"toppressure":{"value":22424460.001957104},"fluiddensity":{},"fluidviscosity":{},"fluidph":{}},{"datetime":{"value":"2022-04-21T16:20:23"},"bottomtemperature":{},"bottomflow":{},"bottompressure":{},"toptemperature":{},"topflow":{"value":0.0},"toppressure":{"value":22368839.65016081},"fluiddensity":{},"fluidviscosity":{},"fluidph":{}},{"datetime":{"value":"2022-04-21T16:21:23"},"bottomtemperature":{},"bottomflow":{},"bottompressure":{},"toptemperature":{},"topflow":{"value":0.0},"toppressure":{"value":22313241.59141309},"fluiddensity":{},"fluidviscosity":{},"fluidph":{}},{"datetime":{"value":"2022-04-21T16:22:23"},"bottomtemperature":{},"bottomflow":{},"bottompressure":{},"toptemperature":{},"topflow":{"value":0.0},"toppressure":{"value":22259487.190764707},"fluiddensity":{},"fluidviscosity":{},"fluidph":{}},{"datetime":{"value":"2022-04-21T16:23:23"},"bottomtemperature":{},"bottomflow":{},"bottompressure":{},"toptemperature":{},"topflow":{"value":0.0},"toppressure":{"value":22206008.810233172},"fluiddensity":{},"fluidviscosity":{},"fluidph":{}},{"datetime":{"value":"2022-04-21T16:24:23"},"bottomtemperature":{},"bottomflow":{},"bottompressure":{},"toptemperature":{},"topflow":{"value":0.0},"toppressure":{"value":22155579.29137528},"fluiddensity":{},"fluidviscosity":{},"fluidph":{}},{"datetime":{"value":"2022-04-21T16:25:23"},"bottomtemperature":{},"bottomflow":{},"bottompressure":{},"toptemperature":{},"topflow":{"value":0.0},"toppressure":{"value":22105384.653915726},"fluiddensity":{},"fluidviscosity":{},"fluidph":{}},{"datetime":{"value":"2022-04-21T16:26:23"},"bottomtemperature":{},"bottomflow":{},"bottompressure":{},"toptemperature":{},"topflow":{"value":0.0},"toppressure":{"value":22055893.971175484},"fluiddensity":{},"fluidviscosity":{},"fluidph":{}},{"datetime":{"value":"2022-04-21T16:27:23"},"bottomtemperature":{},"bottomflow":{},"bottompressure":{},"toptemperature":{},"topflow":{"value":0.0},"toppressure":{"value":22005136.95134631},"fluiddensity":{},"fluidviscosity":{},"fluidph":{}},{"datetime":{"value":"2022-04-21T16:28:23"},"bottomtemperature":{},"bottomflow":{},"bottompressure":{},"toptemperature":{},"topflow":{"value":0.0},"toppressure":{"value":21956450.197306085},"fluiddensity":{},"fluidviscosity":{},"fluidph":{}},{"datetime":{"value":"2022-04-21T16:29:23"},"bottomtemperature":{},"bottomflow":{},"bottompressure":{},"toptemperature":{},"topflow":{"value":0.0},"toppressure":{"value":21913357.38968048},"fluiddensity":{},"fluidviscosity":{},"fluidph":{}}]}]}
