{
    "forecastseries_configs": [
        {
            "name": "Forecast Forge April 2022 Test",
            "description": "Forecasting for forge 2022",
            "starttime": "2022-04-21T13:45:00",
            "endtime": "2022-04-21T17:00:00",
            "forecastinterval": 600,
            "tags": [
                "FORGE",
                "INDUCED"
            ],
            "injectionplan_dir": "/home/indu/workspaces/rt-ramsis/forge_2022/plans",
            "injectionplan_filenames": [
                "plan_double.json",
                "plan_half.json",
                "plan_planned.json",
                "plan_shut-in.json"
            ],
            "altitudemin": -150.0,
            "altitudemax": 150.0,
            "boundingbox": {
                "x_min": 334491.1891,
                "x_max": 334791.18910,
                "y_min": 4263293.6931,
                "y_max": 4263593.6931,
                "srid": "epsg:26912"
            }
        }
    ]
}